samutil/__init__.py
samutil/cli.py
samutil/formatting/__init__.py
samutil/generation/__init__.py
samutil/generation/core.py
samutil/testing/__init__.py
samutil/testing/comparisons.py
samutil/testing/core.py
samutil/testing/decorators.py
samutil/testing/types.py
samutil/testing/utils.py
samutil-0.0.75.dist-info/LICENSE
samutil-0.0.75.dist-info/METADATA
samutil-0.0.75.dist-info/WHEEL
samutil-0.0.75.dist-info/entry_points.txt
samutil-0.0.75.dist-info/top_level.txt
samutil-0.0.75.dist-info/RECORD
